{
  "generated_at": "2026-06-23T06:34:03Z",
  "since": "2026-06-23T05:48:51Z",
  "newly_resolved": [
    {
      "fixture_id": "WC26-M044",
      "team1": "JOR",
      "team2": "ALG",
      "score": "1-2",
      "outcome": 2
    }
  ],
  "title_movers": [
    {
      "country_code": "ALG",
      "before": 0.00713,
      "after": 0.00964,
      "delta": 0.00251
    },
    {
      "country_code": "FRA",
      "before": 0.09762,
      "after": 0.09537,
      "delta": -0.00225
    },
    {
      "country_code": "ENG",
      "before": 0.08188,
      "after": 0.08334,
      "delta": 0.00146
    },
    {
      "country_code": "MAR",
      "before": 0.02027,
      "after": 0.02146,
      "delta": 0.00119
    },
    {
      "country_code": "ESP",
      "before": 0.13611,
      "after": 0.13713,
      "delta": 0.00102
    }
  ],
  "advance_movers": [
    {
      "country_code": "ALG",
      "before": 0.61413,
      "after": 0.7974,
      "delta": 0.18327
    },
    {
      "country_code": "JOR",
      "before": 0.12873,
      "after": 0.0,
      "delta": -0.12873
    },
    {
      "country_code": "AUT",
      "before": 0.91308,
      "after": 0.9322,
      "delta": 0.01912
    },
    {
      "country_code": "CZE",
      "before": 0.32037,
      "after": 0.30834,
      "delta": -0.01203
    },
    {
      "country_code": "URU",
      "before": 0.5188,
      "after": 0.50752,
      "delta": -0.01128
    }
  ]
}